{
  "$defs": {
    "Comment": {
      "properties": {
        "content": {
          "items": {
            "type": "string"
          },
          "title": "Content",
          "type": "array"
        },
        "author": {
          "anyOf": [
            {
              "type": "string"
            },
            {
              "type": "null"
            }
          ],
          "default": null,
          "title": "Author"
        }
      },
      "required": [
        "content"
      ],
      "title": "Comment",
      "type": "object"
    },
    "Metrics": {
      "properties": {
        "values": {
          "additionalProperties": {
            "additionalProperties": {
              "type": "number"
            },
            "propertyNames": {
              "enum": [
                "sdr",
                "si_sdr",
                "l1_freq",
                "log_wmse",
                "aura_stft",
                "aura_mrstft",
                "bleedless",
                "fullness"
              ]
            },
            "type": "object"
          },
          "propertyNames": {
            "enum": [
              "instrum",
              "vocals",
              "drums",
              "bass",
              "other",
              "piano",
              "lead_vocals",
              "back_vocals",
              "guitar",
              "vocals1",
              "vocals2",
              "strings",
              "wind",
              "music",
              "sfx",
              "speech",
              "foreground",
              "background",
              "restored",
              "back",
              "lead",
              "back-instrum",
              "kick",
              "snare",
              "toms",
              "hh",
              "cymbals",
              "hh-cymbals",
              "male",
              "female",
              "violin",
              "ride",
              "crash",
              "dry",
              "reverb",
              "clean",
              "crowd",
              "denoised",
              "noise",
              "similarity",
              "difference",
              "center",
              "keyboards",
              "synthesizer",
              "percussion",
              "orchestral",
              "no_drum-bass",
              "karaoke",
              "beat",
              "downbeat",
              "pitch",
              "confidence",
              "volume",
              "activations",
              "onset",
              "note",
              "contour"
            ]
          },
          "title": "Values",
          "type": "object"
        },
        "source": {
          "anyOf": [
            {
              "const": "mvsep",
              "type": "string"
            },
            {
              "type": "string"
            },
            {
              "type": "null"
            }
          ],
          "default": null,
          "title": "Source"
        }
      },
      "title": "Metrics",
      "type": "object"
    },
    "Model": {
      "properties": {
        "authors": {
          "items": {
            "type": "string"
          },
          "title": "Authors",
          "type": "array"
        },
        "purpose": {
          "anyOf": [
            {
              "enum": [
                "separation",
                "denoise",
                "debleed",
                "dereverb",
                "decrowd",
                "beat_tracking"
              ],
              "type": "string"
            },
            {
              "type": "string"
            }
          ],
          "title": "Purpose"
        },
        "architecture": {
          "anyOf": [
            {
              "enum": [
                "bs_roformer",
                "mel_roformer",
                "mdx23c",
                "scnet",
                "beat_this"
              ],
              "type": "string"
            },
            {
              "type": "string"
            }
          ],
          "title": "Architecture"
        },
        "config_id": {
          "anyOf": [
            {
              "type": "string"
            },
            {
              "type": "null"
            }
          ],
          "default": null,
          "title": "Config Id"
        },
        "created_at": {
          "anyOf": [
            {
              "type": "string"
            },
            {
              "type": "null"
            }
          ],
          "default": null,
          "title": "Created At"
        },
        "output": {
          "items": {
            "enum": [
              "instrum",
              "vocals",
              "drums",
              "bass",
              "other",
              "piano",
              "lead_vocals",
              "back_vocals",
              "guitar",
              "vocals1",
              "vocals2",
              "strings",
              "wind",
              "music",
              "sfx",
              "speech",
              "foreground",
              "background",
              "restored",
              "back",
              "lead",
              "back-instrum",
              "kick",
              "snare",
              "toms",
              "hh",
              "cymbals",
              "hh-cymbals",
              "male",
              "female",
              "violin",
              "ride",
              "crash",
              "dry",
              "reverb",
              "clean",
              "crowd",
              "denoised",
              "noise",
              "similarity",
              "difference",
              "center",
              "keyboards",
              "synthesizer",
              "percussion",
              "orchestral",
              "no_drum-bass",
              "karaoke",
              "beat",
              "downbeat",
              "pitch",
              "confidence",
              "volume",
              "activations",
              "onset",
              "note",
              "contour"
            ],
            "type": "string"
          },
          "minItems": 1,
          "title": "Output",
          "type": "array",
          "unique_items": true
        },
        "status": {
          "anyOf": [
            {
              "const": "tested",
              "type": "string"
            },
            {
              "type": "null"
            }
          ],
          "default": null,
          "title": "Status"
        },
        "metrics": {
          "items": {
            "$ref": "#/$defs/Metrics"
          },
          "title": "Metrics",
          "type": "array"
        },
        "description": {
          "items": {
            "$ref": "#/$defs/Comment"
          },
          "title": "Description",
          "type": "array"
        },
        "resources": {
          "items": {
            "$ref": "#/$defs/Resource"
          },
          "title": "Resources",
          "type": "array"
        },
        "model_size": {
          "anyOf": [
            {
              "type": "integer"
            },
            {
              "type": "null"
            }
          ],
          "default": null,
          "title": "Model Size"
        }
      },
      "required": [
        "authors",
        "purpose",
        "architecture"
      ],
      "title": "Model",
      "type": "object"
    },
    "Resource": {
      "properties": {
        "kind": {
          "enum": [
            "model_ckpt",
            "config_msst",
            "arxiv",
            "other"
          ],
          "title": "Kind",
          "type": "string"
        },
        "url": {
          "title": "Url",
          "type": "string"
        },
        "digest": {
          "anyOf": [
            {
              "type": "string"
            },
            {
              "type": "null"
            }
          ],
          "default": null,
          "title": "Digest"
        }
      },
      "required": [
        "kind",
        "url"
      ],
      "title": "Resource",
      "type": "object"
    }
  },
  "additionalProperties": {
    "$ref": "#/$defs/Model"
  },
  "type": "object"
}